[ {
  "team_id" : 217,
  "team_name" : "Barcelona",
  "lineup" : [ {
    "player_id" : 5203,
    "player_name" : "Sergio Busquets i Burgos",
    "player_nickname" : "Sergio Busquets",
    "jersey_number" : 5,
    "country" : {
      "id" : 214,
      "name" : "Spain"
    }
  }, {
    "player_id" : 5211,
    "player_name" : "Jordi Alba Ramos",
    "player_nickname" : "Jordi Alba",
    "jersey_number" : 18,
    "country" : {
      "id" : 214,
      "name" : "Spain"
    }
  }, {
    "player_id" : 5213,
    "player_name" : "Gerard Piqué Bernabéu",
    "player_nickname" : "Gerard Piqué",
    "jersey_number" : 3,
    "country" : {
      "id" : 214,
      "name" : "Spain"
    }
  }, {
    "player_id" : 5470,
    "player_name" : "Ivan Rakitić",
    "player_nickname" : null,
    "jersey_number" : 4,
    "country" : {
      "id" : 56,
      "name" : "Croatia"
    }
  }, {
    "player_id" : 5487,
    "player_name" : "Antoine Griezmann",
    "player_nickname" : null,
    "jersey_number" : 17,
    "country" : {
      "id" : 78,
      "name" : "France"
    }
  }, {
    "player_id" : 5503,
    "player_name" : "Lionel Andrés Messi Cuccittini",
    "player_nickname" : "Lionel Messi",
    "jersey_number" : 10,
    "country" : {
      "id" : 11,
      "name" : "Argentina"
    }
  }, {
    "player_id" : 6374,
    "player_name" : "Nélson Cabral Semedo",
    "player_nickname" : "Nélson Semedo",
    "jersey_number" : 2,
    "country" : {
      "id" : 183,
      "name" : "Portugal"
    }
  }, {
    "player_id" : 6379,
    "player_name" : "Sergi Roberto Carnicer",
    "player_nickname" : "Sergi Roberto",
    "jersey_number" : 20,
    "country" : {
      "id" : 214,
      "name" : "Spain"
    }
  }, {
    "player_id" : 6826,
    "player_name" : "Clément Lenglet",
    "player_nickname" : null,
    "jersey_number" : 15,
    "country" : {
      "id" : 78,
      "name" : "France"
    }
  }, {
    "player_id" : 8118,
    "player_name" : "Frenkie de Jong",
    "player_nickname" : null,
    "jersey_number" : 21,
    "country" : {
      "id" : 160,
      "name" : "Netherlands"
    }
  }, {
    "player_id" : 11392,
    "player_name" : "Arthur Henrique Ramos de Oliveira Melo",
    "player_nickname" : "Arthur",
    "jersey_number" : 8,
    "country" : {
      "id" : 31,
      "name" : "Brazil"
    }
  }, {
    "player_id" : 20055,
    "player_name" : "Marc-André ter Stegen",
    "player_nickname" : "Marc-André ter Stegen",
    "jersey_number" : 1,
    "country" : {
      "id" : 85,
      "name" : "Germany"
    }
  }, {
    "player_id" : 24841,
    "player_name" : "Ricard Puig Martí",
    "player_nickname" : "Riqui Puig",
    "jersey_number" : 28,
    "country" : {
      "id" : 214,
      "name" : "Spain"
    }
  }, {
    "player_id" : 30756,
    "player_name" : "Anssumane Fati",
    "player_nickname" : "Ansu Fati",
    "jersey_number" : 31,
    "country" : {
      "id" : 255,
      "name" : "International"
    }
  } ]
}, {
  "team_id" : 221,
  "team_name" : "Levante",
  "lineup" : [ {
    "player_id" : 6592,
    "player_name" : "Rúben Miguel Nunes Vezo",
    "player_nickname" : "Rúben Vezo",
    "jersey_number" : 14,
    "country" : {
      "id" : 183,
      "name" : "Portugal"
    }
  }, {
    "player_id" : 6668,
    "player_name" : "José Luis Morales Nogales",
    "player_nickname" : "José Luis Morales",
    "jersey_number" : 11,
    "country" : {
      "id" : 214,
      "name" : "Spain"
    }
  }, {
    "player_id" : 6680,
    "player_name" : "Rubén Rochina Naixes",
    "player_nickname" : "Rubén Rochina",
    "jersey_number" : 16,
    "country" : {
      "id" : 214,
      "name" : "Spain"
    }
  }, {
    "player_id" : 6682,
    "player_name" : "Sergio Postigo Redondo",
    "player_nickname" : "Sergio Postigo",
    "jersey_number" : 15,
    "country" : {
      "id" : 214,
      "name" : "Spain"
    }
  }, {
    "player_id" : 6684,
    "player_name" : "Roger Martí Salvador",
    "player_nickname" : "Roger Martí",
    "jersey_number" : 9,
    "country" : {
      "id" : 214,
      "name" : "Spain"
    }
  }, {
    "player_id" : 6688,
    "player_name" : "José Ángel Gómez Campaña",
    "player_nickname" : "José Campaña",
    "jersey_number" : 24,
    "country" : {
      "id" : 214,
      "name" : "Spain"
    }
  }, {
    "player_id" : 6782,
    "player_name" : "Enis Bardhi",
    "player_nickname" : null,
    "jersey_number" : 10,
    "country" : {
      "id" : 135,
      "name" : "Macedonia, Republic of"
    }
  }, {
    "player_id" : 6784,
    "player_name" : "Antonio García Aranda",
    "player_nickname" : "Toño",
    "jersey_number" : 3,
    "country" : {
      "id" : 214,
      "name" : "Spain"
    }
  }, {
    "player_id" : 11669,
    "player_name" : "Gonzalo Julián Melero Manzanares",
    "player_nickname" : "Gonzalo Melero",
    "jersey_number" : 22,
    "country" : {
      "id" : 214,
      "name" : "Spain"
    }
  }, {
    "player_id" : 11676,
    "player_name" : "Jorge Miramón Santagertrudis",
    "player_nickname" : "Jorge Miramón",
    "jersey_number" : 20,
    "country" : {
      "id" : 214,
      "name" : "Spain"
    }
  }, {
    "player_id" : 12020,
    "player_name" : "Hernâni Jorge Santos Fortes",
    "player_nickname" : "Hernâni",
    "jersey_number" : 8,
    "country" : {
      "id" : 183,
      "name" : "Portugal"
    }
  }, {
    "player_id" : 17303,
    "player_name" : "Nikola Vukčević",
    "player_nickname" : null,
    "jersey_number" : 17,
    "country" : {
      "id" : 152,
      "name" : "Montenegro"
    }
  }, {
    "player_id" : 21147,
    "player_name" : "Borja Mayoral Moya",
    "player_nickname" : "Borja Mayoral",
    "jersey_number" : 21,
    "country" : {
      "id" : 214,
      "name" : "Spain"
    }
  }, {
    "player_id" : 23344,
    "player_name" : "Aitor Fernández Abarisketa",
    "player_nickname" : "Aitor Fernández",
    "jersey_number" : 13,
    "country" : {
      "id" : 214,
      "name" : "Spain"
    }
  } ]
} ]