[ {
  "team_id" : 778,
  "team_name" : "Japan",
  "lineup" : [ {
    "player_id" : 3175,
    "player_name" : "Eiji Kawashima",
    "player_nickname" : null,
    "jersey_number" : 1,
    "country" : {
      "id" : 114,
      "name" : "Japan"
    }
  }, {
    "player_id" : 3300,
    "player_name" : "Maya Yoshida",
    "player_nickname" : null,
    "jersey_number" : 22,
    "country" : {
      "id" : 114,
      "name" : "Japan"
    }
  }, {
    "player_id" : 3530,
    "player_name" : "Hiroki Sakai",
    "player_nickname" : null,
    "jersey_number" : 19,
    "country" : {
      "id" : 114,
      "name" : "Japan"
    }
  }, {
    "player_id" : 3810,
    "player_name" : "Shinji Okazaki",
    "player_nickname" : null,
    "jersey_number" : 9,
    "country" : {
      "id" : 114,
      "name" : "Japan"
    }
  }, {
    "player_id" : 5679,
    "player_name" : "Yūya Ōsako",
    "player_nickname" : null,
    "jersey_number" : 15,
    "country" : {
      "id" : 114,
      "name" : "Japan"
    }
  }, {
    "player_id" : 5681,
    "player_name" : "Makoto Hasebe",
    "player_nickname" : null,
    "jersey_number" : 17,
    "country" : {
      "id" : 114,
      "name" : "Japan"
    }
  }, {
    "player_id" : 5682,
    "player_name" : "Gen Shōji",
    "player_nickname" : null,
    "jersey_number" : 3,
    "country" : {
      "id" : 114,
      "name" : "Japan"
    }
  }, {
    "player_id" : 5683,
    "player_name" : "Keisuke Honda",
    "player_nickname" : null,
    "jersey_number" : 4,
    "country" : {
      "id" : 114,
      "name" : "Japan"
    }
  }, {
    "player_id" : 5684,
    "player_name" : "Shinji Kagawa",
    "player_nickname" : null,
    "jersey_number" : 10,
    "country" : {
      "id" : 114,
      "name" : "Japan"
    }
  }, {
    "player_id" : 5687,
    "player_name" : "Takashi Inui",
    "player_nickname" : null,
    "jersey_number" : 14,
    "country" : {
      "id" : 114,
      "name" : "Japan"
    }
  }, {
    "player_id" : 5690,
    "player_name" : "Yuto Nagatomo",
    "player_nickname" : null,
    "jersey_number" : 5,
    "country" : {
      "id" : 114,
      "name" : "Japan"
    }
  }, {
    "player_id" : 5693,
    "player_name" : "Gaku Shibasaki",
    "player_nickname" : null,
    "jersey_number" : 7,
    "country" : {
      "id" : 114,
      "name" : "Japan"
    }
  }, {
    "player_id" : 5694,
    "player_name" : "Hotaru Yamaguchi",
    "player_nickname" : null,
    "jersey_number" : 16,
    "country" : {
      "id" : 114,
      "name" : "Japan"
    }
  }, {
    "player_id" : 5697,
    "player_name" : "Genki Haraguchi",
    "player_nickname" : null,
    "jersey_number" : 8,
    "country" : {
      "id" : 114,
      "name" : "Japan"
    }
  }, {
    "player_id" : 6191,
    "player_name" : "Takashi Usami",
    "player_nickname" : null,
    "jersey_number" : 11,
    "country" : {
      "id" : 114,
      "name" : "Japan"
    }
  }, {
    "player_id" : 6337,
    "player_name" : "Yoshinori Muto",
    "player_nickname" : null,
    "jersey_number" : 13,
    "country" : {
      "id" : 114,
      "name" : "Japan"
    }
  }, {
    "player_id" : 6338,
    "player_name" : "Tomoaki Makino",
    "player_nickname" : null,
    "jersey_number" : 20,
    "country" : {
      "id" : 114,
      "name" : "Japan"
    }
  }, {
    "player_id" : 6339,
    "player_name" : "Gotoku Sakai",
    "player_nickname" : null,
    "jersey_number" : 21,
    "country" : {
      "id" : 114,
      "name" : "Japan"
    }
  }, {
    "player_id" : 23721,
    "player_name" : "Wataru Endo",
    "player_nickname" : null,
    "jersey_number" : 6,
    "country" : {
      "id" : 114,
      "name" : "Japan"
    }
  }, {
    "player_id" : 24015,
    "player_name" : "Naomichi Ueda",
    "player_nickname" : null,
    "jersey_number" : 2,
    "country" : {
      "id" : 114,
      "name" : "Japan"
    }
  }, {
    "player_id" : 37194,
    "player_name" : "Ryota Oshima",
    "player_nickname" : null,
    "jersey_number" : 18,
    "country" : {
      "id" : 114,
      "name" : "Japan"
    }
  }, {
    "player_id" : 37486,
    "player_name" : "Masaaki Higashiguchi",
    "player_nickname" : null,
    "jersey_number" : 12,
    "country" : {
      "id" : 114,
      "name" : "Japan"
    }
  }, {
    "player_id" : 42236,
    "player_name" : "Kosuke Nakamura",
    "player_nickname" : null,
    "jersey_number" : 23,
    "country" : {
      "id" : 114,
      "name" : "Japan"
    }
  } ]
}, {
  "team_id" : 769,
  "team_name" : "Colombia",
  "lineup" : [ {
    "player_id" : 3279,
    "player_name" : "José Heriberto Izquierdo Mena",
    "player_nickname" : "José Izquierdo",
    "jersey_number" : 21,
    "country" : {
      "id" : 49,
      "name" : "Colombia"
    }
  }, {
    "player_id" : 3445,
    "player_name" : "Radamel Falcao García Zárate",
    "player_nickname" : "Falcao",
    "jersey_number" : 9,
    "country" : {
      "id" : 49,
      "name" : "Colombia"
    }
  }, {
    "player_id" : 3494,
    "player_name" : "Davinson Sánchez Mina",
    "player_nickname" : "Davinson Sánchez",
    "jersey_number" : 23,
    "country" : {
      "id" : 49,
      "name" : "Colombia"
    }
  }, {
    "player_id" : 4276,
    "player_name" : "David Ospina Ramírez",
    "player_nickname" : "David Ospina",
    "jersey_number" : 1,
    "country" : {
      "id" : 49,
      "name" : "Colombia"
    }
  }, {
    "player_id" : 5678,
    "player_name" : "Jefferson Andrés Lerma Solís",
    "player_nickname" : "Jefferson Lerma",
    "jersey_number" : 16,
    "country" : {
      "id" : 49,
      "name" : "Colombia"
    }
  }, {
    "player_id" : 5680,
    "player_name" : "Oscar Fabián Murillo Murillo",
    "player_nickname" : "Óscar Murillo",
    "jersey_number" : 3,
    "country" : {
      "id" : 49,
      "name" : "Colombia"
    }
  }, {
    "player_id" : 5685,
    "player_name" : "Carlos Alberto Sánchez Moreno",
    "player_nickname" : "Carlos Sánchez",
    "jersey_number" : 6,
    "country" : {
      "id" : 49,
      "name" : "Colombia"
    }
  }, {
    "player_id" : 5686,
    "player_name" : "Wílmar Enrique Barrios Terán",
    "player_nickname" : "Wílmar Barrios",
    "jersey_number" : 5,
    "country" : {
      "id" : 49,
      "name" : "Colombia"
    }
  }, {
    "player_id" : 5688,
    "player_name" : "Carlos Arturo Bacca Ahumada",
    "player_nickname" : "Carlos Bacca",
    "jersey_number" : 7,
    "country" : {
      "id" : 49,
      "name" : "Colombia"
    }
  }, {
    "player_id" : 5689,
    "player_name" : "Juan Guillermo Cuadrado Bello",
    "player_nickname" : "Juan Cuadrado",
    "jersey_number" : 11,
    "country" : {
      "id" : 49,
      "name" : "Colombia"
    }
  }, {
    "player_id" : 5691,
    "player_name" : "Johan Andrés Mojica Palacio",
    "player_nickname" : "Johan Mojica",
    "jersey_number" : 17,
    "country" : {
      "id" : 49,
      "name" : "Colombia"
    }
  }, {
    "player_id" : 5692,
    "player_name" : "Juan Fernando Quintero Paniagua",
    "player_nickname" : "Juan Fernando Quintero",
    "jersey_number" : 20,
    "country" : {
      "id" : 49,
      "name" : "Colombia"
    }
  }, {
    "player_id" : 5695,
    "player_name" : "James David Rodríguez Rubio",
    "player_nickname" : "James Rodríguez",
    "jersey_number" : 10,
    "country" : {
      "id" : 49,
      "name" : "Colombia"
    }
  }, {
    "player_id" : 5696,
    "player_name" : "Santiago Arias Naranjo",
    "player_nickname" : "Santiago Arias",
    "jersey_number" : 4,
    "country" : {
      "id" : 49,
      "name" : "Colombia"
    }
  }, {
    "player_id" : 6192,
    "player_name" : "Abel Enrique Aguilar Tapia",
    "player_nickname" : "Abel Aguilar",
    "jersey_number" : 8,
    "country" : {
      "id" : 49,
      "name" : "Colombia"
    }
  }, {
    "player_id" : 6193,
    "player_name" : "Andrés Mateus Uribe Villa",
    "player_nickname" : "Mateus Uribe",
    "jersey_number" : 15,
    "country" : {
      "id" : 49,
      "name" : "Colombia"
    }
  }, {
    "player_id" : 6196,
    "player_name" : "Yerry Fernando Mina González",
    "player_nickname" : "Yerry Mina",
    "jersey_number" : 13,
    "country" : {
      "id" : 49,
      "name" : "Colombia"
    }
  }, {
    "player_id" : 6333,
    "player_name" : "Miguel Ángel Borja Hernández",
    "player_nickname" : "Miguel Borja",
    "jersey_number" : 19,
    "country" : {
      "id" : 49,
      "name" : "Colombia"
    }
  }, {
    "player_id" : 6334,
    "player_name" : "Luis Fernando Muriel Fruto",
    "player_nickname" : "Luis Muriel",
    "jersey_number" : 14,
    "country" : {
      "id" : 49,
      "name" : "Colombia"
    }
  }, {
    "player_id" : 6360,
    "player_name" : "Cristian Eduardo Zapata Valencia",
    "player_nickname" : "Cristián Zapata",
    "jersey_number" : 2,
    "country" : {
      "id" : 49,
      "name" : "Colombia"
    }
  }, {
    "player_id" : 27225,
    "player_name" : "Camilo Andrés Vargas Gil",
    "player_nickname" : "Camilo Vargas",
    "jersey_number" : 12,
    "country" : {
      "id" : 49,
      "name" : "Colombia"
    }
  }, {
    "player_id" : 27417,
    "player_name" : "Farid Alfonso Díaz Rhenals",
    "player_nickname" : "Farid Díaz",
    "jersey_number" : 18,
    "country" : {
      "id" : 49,
      "name" : "Colombia"
    }
  }, {
    "player_id" : 27470,
    "player_name" : "José Fernando Cuadrado Romero",
    "player_nickname" : "José Cuadrado",
    "jersey_number" : 22,
    "country" : {
      "id" : 49,
      "name" : "Colombia"
    }
  } ]
} ]